Metadata-Version: 2.1
Name: xadmin2
Version: 2.0.4
Summary: Drop-in replacement of Django admin comes with lots of goodies, fully extensible with plugin support, pretty UI based on Twitter Bootstrap.
Home-page: http://www.xadmin.io
Author: wgbbiao
Author-email: wgb237@163.com
License: Copyright (c) Django Xadmin and individual contributors.
